podmena/__init__.py
podmena/cli.py
podmena/config.py
podmena/group.py
podmena/resources/commit-msg
podmena/resources/emoji-db
podmena/utils.py
podmena-0.6.1.dist-info/entry_points.txt
podmena-0.6.1.dist-info/LICENSE.txt
podmena-0.6.1.dist-info/WHEEL
podmena-0.6.1.dist-info/METADATA
podmena-0.6.1.dist-info/RECORD
