Metadata-Version: 2.1
Name: podmena
Version: 0.6.1
Summary: Enhance your commit messages with emoji
Home-page: https://github.com/bmwant/podmena
License: Unlicense
Keywords: git,hook,fun,emoji,commit
Author: Misha Behersky
Author-email: bmwant@gmail.com
Requires-Python: >=3.6.2,<4.0.0
Classifier: Development Status :: 4 - Beta
Classifier: Environment :: Console
Classifier: Intended Audience :: Developers
Classifier: License :: Other/Proprietary License
Classifier: Programming Language :: Python :: 3
Classifier: Programming Language :: Python :: 3 :: Only
Classifier: Programming Language :: Python :: 3.10
Classifier: Programming Language :: Python :: 3.11
Classifier: Programming Language :: Python :: 3.6
Classifier: Programming Language :: Python :: 3.7
Classifier: Programming Language :: Python :: 3.8
Classifier: Programming Language :: Python :: 3.9
Classifier: Programming Language :: Unix Shell
Classifier: Topic :: Software Development :: Build Tools
Classifier: Topic :: Software Development :: Version Control :: Git
Classifier: Topic :: Utilities
Requires-Dist: click (>=8.0,<9.0)
Project-URL: Blog post, https://bmwlog.pp.ua/
Project-URL: Repository, https://github.com/bmwant/podmena
